{
  "total_ideas": 36,
  "total_clusters": 5,
  "clusters": [
    {
      "id": 0,
      "topic": "Housing",
      "name": "Staten Island Housing",
      "summary": "10 citizens advocating for housing improvements",
      "action": "Review and prioritize these housing-related suggestions",
      "consensus": "High",
      "node_count": 10,
      "demands": [],
      "synthesized_actions": [],
      "nodes": [
        {
          "id": 1,
          "username": "@NYCPlanning",
          "summary": "Accessory dwelling units (ADUs) are a proven way to create housing & help homeowners. Homeowners filing to build them across boroughs including Staten Island.",
          "date": "2025-12-05",
          "link": "https://x.com/NYCPlanning/status/1996951955885765018"
        },
        {
          "id": 2,
          "username": "@AriReddy",
          "summary": "Highlighting past high permitting in Manhattan (13,000 units in 1960 vs low in 1990s) to argue for less restrictive regulations to allow more housing.",
          "date": "2025-12-05",
          "link": "https://x.com/AriReddy/status/1996943460193206283"
        },
        {
          "id": 3,
          "username": "@privatelexicon",
          "summary": "Propose 150k homes in Bronx, 100k in Manhattan (infill + conversions), 250k in Staten Island/South Brooklyn with beauty, density, and green space.",
          "date": "2025-12-02",
          "link": "https://x.com/privatelexicon/status/1995938100787495250"
        },
        {
          "id": 4,
          "username": "@BadTakeEnjoyer",
          "summary": "Build a subway tunnel to Staten Island for 7-10 min trips and enable much more housing on the island.",
          "date": "2025-12-01",
          "link": "https://x.com/BadTakeEnjoyer/status/1995193598900686890"
        },
        {
          "id": 5,
          "username": "@BadTakeEnjoyer",
          "summary": "Apply Tokyo-style zoning to Staten Island as experiment, use tax revenue to extend subway lines to the island.",
          "date": "2025-12-01",
          "link": "https://x.com/BadTakeEnjoyer/status/1995531427593494550"
        },
        {
          "id": 6,
          "username": "@CelestinAustin",
          "summary": "Criticizes council members for proposing housing on inconvenient islands while their districts build none; calls for housing in existing neighborhoods.",
          "date": "2025-11-30",
          "link": "https://x.com/CelestinAustin/status/1994876419218800720"
        },
        {
          "id": 7,
          "username": "@DanBiancoNYC",
          "summary": "Build affordable housing first on helipads ruining enjoyment of Governor\u2019s Island (satirical support for more housing there).",
          "date": "2025-11-30",
          "link": "https://x.com/DanBiancoNYC/status/1994890217720091036"
        },
        {
          "id": 8,
          "username": "@roselialescrime",
          "summary": "Build dense, affordable city-run 5+ story housing complexes (not for-profit).",
          "date": "2025-11-30",
          "link": "https://x.com/roselialescrime/status/1994943810267484220"
        },
        {
          "id": 16,
          "username": "@TransAlt",
          "summary": "Set minimum sidewalk width of 8 feet tied to zoning; fund widening program for substandard sidewalks.",
          "date": "2022-11-22",
          "link": "https://x.com/TransAlt/status/1595137036037636107"
        },
        {
          "id": 9,
          "username": "@UrbanCourtyard",
          "summary": "Dense, walkable neighborhoods connected by extensive passenger rail to solve urban issues.",
          "date": "2025-11-26",
          "link": "https://x.com/UrbanCourtyard/status/1993771998120702091"
        }
      ]
    },
    {
      "id": 1,
      "topic": "Sidewalks",
      "name": "Pedestrian Infrastructure",
      "summary": "8 citizens advocating for sidewalks improvements",
      "action": "Review and prioritize these sidewalks-related suggestions",
      "consensus": "High",
      "node_count": 8,
      "demands": [],
      "synthesized_actions": [],
      "nodes": [
        {
          "id": 10,
          "username": "@UrbanCourtyard",
          "summary": "Narrow streets, widen sidewalks, extend property lines into streets for more space/revenue.",
          "date": "2025-06-06",
          "link": "https://x.com/UrbanCourtyard/status/1931126086139560056"
        },
        {
          "id": 13,
          "username": "@BrentToderian",
          "summary": "Make sidewalks bigger and better (double-loaded sidewalks).",
          "date": "2024-11-09",
          "link": "https://x.com/BrentToderian/status/1855292918736773311"
        },
        {
          "id": 17,
          "username": "@BrentToderian",
          "summary": "Implement \u201cschool streets\u201d (car-free blocks beside schools during drop-off/pick-up) for safety and enjoyment.",
          "date": "2021-12-16",
          "link": "https://x.com/BrentToderian/status/1471276645503827970"
        },
        {
          "id": 18,
          "username": "@BrentToderian",
          "summary": "Implement \u201cschool streets\u201d (car-free blocks beside schools).",
          "date": "2021-11-06",
          "link": "https://x.com/BrentToderian/status/1457008377104519168"
        },
        {
          "id": 22,
          "username": "@MS_Neg",
          "summary": "Urbanize with connecting sidewalks, updated crosswalks, mid/small intersections.",
          "date": "2025-12-03",
          "link": "https://x.com/MS_Neg/status/1996018600029855811"
        },
        {
          "id": 11,
          "username": "@catculley",
          "summary": "Fantastic opportunity for human-focused street redesign: wide sidewalks, trees, outdoor dining, benches.",
          "date": "2025-01-11",
          "link": "https://x.com/catculley/status/1878062321316036885"
        },
        {
          "id": 12,
          "username": "@jasonc_nc",
          "summary": "Focus on safety (more officers, stop panhandling), expand outdoor dining/leisure, streetscape improvements, public investments over subsidies.",
          "date": "2024-12-10",
          "link": "https://x.com/jasonc_nc/status/1866531214280028270"
        },
        {
          "id": 24,
          "username": "@UrbanCourtyard",
          "summary": "Support walkable urban neighborhoods with social interest, public conveniences, street-level retail.",
          "date": "2025-02-05",
          "link": "https://x.com/UrbanCourtyard/status/1886975365823778897"
        }
      ]
    },
    {
      "id": 2,
      "topic": "Green Space",
      "name": "Green Infrastructure",
      "summary": "2 citizens advocating for green space improvements",
      "action": "Review and prioritize these green space-related suggestions",
      "consensus": "Medium",
      "node_count": 2,
      "demands": [],
      "synthesized_actions": [],
      "nodes": [
        {
          "id": 14,
          "username": "@TransAlt",
          "summary": "Increase permeable infrastructure/replace car space with green space in flood-prone areas for resilience.",
          "date": "2023-09-29",
          "link": "https://x.com/TransAlt/status/1707858007583822153"
        },
        {
          "id": 31,
          "username": "NYDailyNews",
          "summary": "Reinstated city plan for southern McGuinness Boulevard in Greenpoint",
          "date": "2024-10-02",
          "link": "Brooklyn"
        }
      ]
    },
    {
      "id": 3,
      "topic": "Transit",
      "name": "Bus Lane Expansion",
      "summary": "15 citizens advocating for transit improvements",
      "action": "Review and prioritize these transit-related suggestions",
      "consensus": "High",
      "node_count": 15,
      "demands": [],
      "synthesized_actions": [],
      "nodes": [
        {
          "id": 15,
          "username": "@rustbeltenjoyer",
          "summary": "More buses/routes, turn dead malls into community centers/art spaces/indoor plazas, foot/cycle paths to parks/transit.",
          "date": "2023-07-13",
          "link": "https://x.com/rustbeltenjoyer/status/1679531890988965888"
        },
        {
          "id": 34,
          "username": "VickieforNYC",
          "summary": "Incident highlights dangers in protected bike lanes near stopped school buses where children are active; calls for registration",
          "date": "2024-11-13",
          "link": "licensing"
        },
        {
          "id": 30,
          "username": "TransAlt",
          "summary": "Protected bike lane proposal on Brooklyn and Kingston Avenues in East Flatbush (Community Board 9) deemed essential due to 10 schools within one block; project establishes first protected bike connections in area lacking such infrastructure.",
          "date": "2024-10-02",
          "link": "https://x.com/TransAlt/status/1841481139149512831"
        },
        {
          "id": 32,
          "username": "NYC_DOT",
          "summary": "Construction underway for 1.5-mile parking-protected bike lane on Bedford Avenue in Bed-Stuy",
          "date": "2024-09-10",
          "link": "Brooklyn"
        },
        {
          "id": 33,
          "username": "BikeSouthBklyn",
          "summary": "NYC DOT school safety project proposes two-way protected bike lane on 7th Avenue between 86th Street and Poly Place in southern Brooklyn (CB 10)",
          "date": "2024-06-11",
          "link": "focusing on improved crossings and separation for students commuting by bike."
        },
        {
          "id": 35,
          "username": "PeteSikora1",
          "summary": "Completed protected bike lane on Court Street in Brooklyn (near downtown schools) reduces car speeds",
          "date": "2025-12-03",
          "link": "improves crosswalks"
        },
        {
          "id": 36,
          "username": "infopobn",
          "summary": "Ongoing litigation challenges NYC DOT protected bike lane on Court Street in Brooklyn",
          "date": "2025-12-06",
          "link": "strengthened by Queens precedent requiring removal of 31st Street bike lane"
        },
        {
          "id": 27,
          "username": "JCHudsonMedia",
          "summary": "Radio discussion on proposal to remove existing protected bike lane in unspecified Brooklyn location",
          "date": "2025-07-14",
          "link": "contextualized alongside school funding debates"
        },
        {
          "id": 28,
          "username": "StreetsblogNYC",
          "summary": "Brooklyn judge halts NYC DOT's plan to tear up three blocks of protected bike lane on Bedford Avenue in Williamsburg",
          "date": "2025-06-18",
          "link": "preserving the infrastructure amid community and safety concerns near residential areas including schools."
        },
        {
          "id": 23,
          "username": "@JohnSurico",
          "summary": "Repurpose space near subway stations with wider sidewalks, larger bus shelters, bike parking, benches, micro forests, public restrooms.",
          "date": "2025-11-30",
          "link": "https://x.com/JohnSurico/status/1994940859339739375"
        },
        {
          "id": 29,
          "username": "UnitedJewish",
          "summary": "United Jewish Organizations statement criticizes NYC DOT's redesigned protected bike lane on Bedford Avenue in Williamsburg and North Brooklyn for failing to address pedestrian safety risks",
          "date": "2024-10-29",
          "link": "particularly for school children crossing the street."
        },
        {
          "id": 20,
          "username": "@JohnnyWalsh__",
          "summary": "N-S bus lanes, expanded elevated bike lanes, priority signaling (context applied to NYC-style improvements).",
          "date": "2025-12-04",
          "link": "https://x.com/JohnnyWalsh__/status/1996401929636008182"
        },
        {
          "id": 21,
          "username": "@RolandB3",
          "summary": "More cops/tickets, red light/speed cameras, build pedestrian/bike infrastructure and sidewalks, narrow street lanes.",
          "date": "2025-12-04",
          "link": "https://x.com/RolandB3/status/1996636091651383608"
        },
        {
          "id": 26,
          "username": "@DaveCoIon",
          "summary": "100 miles bus lanes in two years, subsidize e-bikes, expand sidewalks, install public sidewalk seating/bathrooms.",
          "date": "2020-08-07",
          "link": "https://x.com/DaveCoIon/status/1291816245436862464"
        },
        {
          "id": 25,
          "username": "@signulll",
          "summary": "Pedestrianize 5th Ave with trees/gardens, light rail on 6th Ave, vibrant vendors/food/arts/music.",
          "date": "2025-01-15",
          "link": "https://x.com/signulll/status/1879543963138584959"
        }
      ]
    },
    {
      "id": 4,
      "topic": "Safety",
      "name": "Public Safety",
      "summary": "1 citizens advocating for safety improvements",
      "action": "Review and prioritize these safety-related suggestions",
      "consensus": "Medium",
      "node_count": 1,
      "demands": [],
      "synthesized_actions": [],
      "nodes": [
        {
          "id": 19,
          "username": "@bikesnobnyc",
          "summary": "Parking/delivery reform, automated enforcement, congestion pricing, close sections to traffic; reduce driving by set percentage.",
          "date": "2019-07-25",
          "link": "https://x.com/bikesnobnyc/status/1154393395688816640"
        }
      ]
    }
  ]
}